fastfingertips/__init__.py
fastfingertips/datetime_utils.py
fastfingertips/file_utils.py
fastfingertips/string_utils.py
fastfingertips/terminal_utils.py
fastfingertips/url_utils.py
fastfingertips-0.1.3.dist-info/licenses/LICENSE
fastfingertips-0.1.3.dist-info/METADATA
fastfingertips-0.1.3.dist-info/WHEEL
fastfingertips-0.1.3.dist-info/top_level.txt
fastfingertips-0.1.3.dist-info/RECORD
