Metadata-Version: 2.4
Name: fastfingertips
Version: 0.1.3
Summary: A collection of personal Python utility functions to reduce code repetition.
Author-email: FastFingertips <fastfingertips@gmail.com>
Project-URL: Homepage, https://github.com/fastfingertips/fastfingertips-pypi
Project-URL: Repository, https://github.com/fastfingertips/fastfingertips-pypi
Project-URL: Issues, https://github.com/fastfingertips/fastfingertips-pypi/issues
Keywords: utility,helper,tools,fastfingertips,python
Classifier: Programming Language :: Python :: 3
Classifier: License :: OSI Approved :: MIT License
Classifier: Operating System :: OS Independent
Requires-Python: >=3.7
License-File: LICENSE
Dynamic: license-file
